payrave
